RuheShixianZijiDeJquery/README.md
RuheShixianZijiDeJquery/__init__.py
RuheShixianZijiDeJquery/__main__.py
RuheShixianZijiDeJquery/file.epub
RuheShixianZijiDeJquery/index.html
RuheShixianZijiDeJquery/css/__init__.py
RuheShixianZijiDeJquery/css/annotations.css
RuheShixianZijiDeJquery/css/main.css
RuheShixianZijiDeJquery/css/normalize.css
RuheShixianZijiDeJquery/css/popup.css
RuheShixianZijiDeJquery/font/__init__.py
RuheShixianZijiDeJquery/font/fontello.eot
RuheShixianZijiDeJquery/font/fontello.svg
RuheShixianZijiDeJquery/font/fontello.ttf
RuheShixianZijiDeJquery/font/fontello.woff
RuheShixianZijiDeJquery/img/__init__.py
RuheShixianZijiDeJquery/img/annotator-glyph-sprite.png
RuheShixianZijiDeJquery/img/annotator-icon-sprite.png
RuheShixianZijiDeJquery/img/apple-touch-icon.png
RuheShixianZijiDeJquery/img/cancelfullscreen.png
RuheShixianZijiDeJquery/img/close.png
RuheShixianZijiDeJquery/img/fullscreen.png
RuheShixianZijiDeJquery/img/loader.gif
RuheShixianZijiDeJquery/img/menu-icon.png
RuheShixianZijiDeJquery/img/save.png
RuheShixianZijiDeJquery/img/saved.png
RuheShixianZijiDeJquery/img/settings-s.png
RuheShixianZijiDeJquery/img/settings.png
RuheShixianZijiDeJquery/img/star.png
RuheShixianZijiDeJquery/js/__init__.py
RuheShixianZijiDeJquery/js/epub.js
RuheShixianZijiDeJquery/js/epub.min.js
RuheShixianZijiDeJquery/js/epub.min.map
RuheShixianZijiDeJquery/js/hooks.min.js
RuheShixianZijiDeJquery/js/hooks.min.map
RuheShixianZijiDeJquery/js/reader.js
RuheShixianZijiDeJquery/js/reader.js.map
RuheShixianZijiDeJquery/js/reader.min.js
RuheShixianZijiDeJquery/js/reader.min.map
RuheShixianZijiDeJquery/js/hooks/__init__.py
RuheShixianZijiDeJquery/js/hooks/extensions/__init__.py
RuheShixianZijiDeJquery/js/hooks/extensions/highlight.js
RuheShixianZijiDeJquery/js/libs/__init__.py
RuheShixianZijiDeJquery/js/libs/jquery.min.js
RuheShixianZijiDeJquery/js/libs/localforage.min.js
RuheShixianZijiDeJquery/js/libs/screenfull.js
RuheShixianZijiDeJquery/js/libs/screenfull.min.js
ruhe_shixian_ziji_de_jquery-2024.3.2.0.dist-info/METADATA
ruhe_shixian_ziji_de_jquery-2024.3.2.0.dist-info/WHEEL
ruhe_shixian_ziji_de_jquery-2024.3.2.0.dist-info/entry_points.txt
ruhe_shixian_ziji_de_jquery-2024.3.2.0.dist-info/top_level.txt
ruhe_shixian_ziji_de_jquery-2024.3.2.0.dist-info/RECORD
